Metadata-Version: 2.4
Name: geneprep
Version: 0.1.1
Summary: Published package for GenePrep project
Author-email: Yue Xue <yx2876@columbia.edu>, Sirihaasa Nallamothu <sn37@illinois.edu>
License-Expression: MIT
Project-URL: Homepage, https://github.com/YueXu-2001/GenePrep
Requires-Python: >=3.7
License-File: LICENSE
Requires-Dist: openai
Requires-Dist: python-dotenv
Requires-Dist: backoff
Requires-Dist: dill
Requires-Dist: nbconvert
Requires-Dist: nbformat
Requires-Dist: numpy
Requires-Dist: pandas
Requires-Dist: protobuf
Requires-Dist: scikit-learn
Requires-Dist: statsmodels
Requires-Dist: tqdm
Requires-Dist: biopython
Requires-Dist: psutil
Requires-Dist: pynvml
Requires-Dist: anthropic
Requires-Dist: google.generativeai
Requires-Dist: ollama
Dynamic: license-file
